c_explainer.cpython-39-aarch64-linux-gnu.so
pypi/old_setup.py
pypi/publish_pypi.py
pyxai/Builder.py
pyxai/Explainer.py
pyxai/Learning.py
pyxai/Tools.py
pyxai/__init__.py
pyxai/__main__.py
pyxai/convert.py
pyxai/setup.py
pyxai/examples/BT/GUI-mnist38.py
pyxai/examples/BT/builder-arxiv-2511.03169-3.py
pyxai/examples/BT/builder-simple.py
pyxai/examples/BT/simple.py
pyxai/examples/BT/regression/builder-regression.py
pyxai/examples/BT/regression/simple-regression.py
pyxai/examples/Converters/converter-adult.py
pyxai/examples/Converters/converter-arrowhead.py
pyxai/examples/Converters/converter-australian.py
pyxai/examples/Converters/converter-balance-scale.py
pyxai/examples/Converters/converter-bank.py
pyxai/examples/Converters/converter-biodegradation.py
pyxai/examples/Converters/converter-breast-tumor.py
pyxai/examples/Converters/converter-bupa.py
pyxai/examples/Converters/converter-christine.py
pyxai/examples/Converters/converter-cifar.py
pyxai/examples/Converters/converter-cleveland.py
pyxai/examples/Converters/converter-cnae.py
pyxai/examples/Converters/converter-compas.py
pyxai/examples/Converters/converter-contraceptive.py
pyxai/examples/Converters/converter-default-paiement.py
pyxai/examples/Converters/converter-dexter.py
pyxai/examples/Converters/converter-divorce.py
pyxai/examples/Converters/converter-german.py
pyxai/examples/Converters/converter-gisette.py
pyxai/examples/Converters/converter-melb.py
pyxai/examples/Converters/converter-mnist.py
pyxai/examples/Converters/converter-nerve.py
pyxai/examples/Converters/converter-regression.py
pyxai/examples/Converters/converter-spambase.py
pyxai/examples/Converters/converter-wine.py
pyxai/examples/Converters/bad/converter-dorothea.py
pyxai/examples/DT/GUI-cifar.py
pyxai/examples/DT/GUI-mnist38-contrastives.py
pyxai/examples/DT/GUI-mnist38.py
pyxai/examples/DT/base.py
pyxai/examples/DT/builder-anchored.py
pyxai/examples/DT/builder-loan.py
pyxai-1.1.1.dist-info/METADATA
pyxai-1.1.1.dist-info/WHEEL
pyxai-1.1.1.dist-info/top_level.txt
pyxai-1.1.1.dist-info/RECORD
pyxai-1.1.1.dist-info/licenses/LICENSE
