Metadata-Version: 2.4
Name: pyxai
Version: 1.1.1
Summary: Explaining Machine Learning Classifiers in Python
Author-email: Gilles Audemard <audemard@cril.fr>, Steve Bellart <bellart@cril.fr>, Louenas Bounia <bounia@cril.fr>, Jean-Marie Lagniez <lagniez@cril.fr>, Pierre Marquis <marquis@cril.fr>, Nicolas Szczepanski <szczepanski@cril.fr>
Maintainer-email: Gilles Audemard <audemard@cril.fr>, Nicolas Szczepanski <szczepanski@cril.fr>
License: MIT
Project-URL: Documentation, http://www.cril.univ-artois.fr/pyxai/
Project-URL: Installation, http://www.cril.univ-artois.fr/pyxai/documentation/installation/
Project-URL: Git, https://github.com/crillab/pyxai
Keywords: XAI,AI,ML,explainable,learning
Classifier: Topic :: Scientific/Engineering :: Artificial Intelligence
Classifier: Topic :: Education
Requires-Python: >=3.7
License-File: LICENSE
Requires-Dist: lxml
Requires-Dist: numpy
Requires-Dist: wheel
Requires-Dist: pandas
Requires-Dist: termcolor
Requires-Dist: shap
Requires-Dist: wordfreq
Requires-Dist: python-sat[aiger,pblib]
Requires-Dist: xgboost==1.7.3
Requires-Dist: pycsp3
Requires-Dist: matplotlib
Requires-Dist: dill
Requires-Dist: lightgbm
Requires-Dist: docplex
Requires-Dist: ortools
Requires-Dist: packaging
Provides-Extra: gui
Requires-Dist: pyqt6; extra == "gui"
Dynamic: license-file
